MANIFEST.in
README.md
setup.cfg
setup.py
jsog3/__init__.py
jsog3/jsog.py
jsog3.egg-info/PKG-INFO
jsog3.egg-info/SOURCES.txt
jsog3.egg-info/dependency_links.txt
jsog3.egg-info/top_level.txt