Metadata-Version: 1.1
Name: jsog3
Version: 2.0.4
Summary: JSOG serializer and deserializer
Home-page: https://github.com/simoneggler/jsog-python
Author: Simon Eggler
Author-email: simon.eggler@gmx.net
License: MIT License
Keywords: jsog json
Platform: UNKNOWN
Classifier: Development Status :: 5 - Production/Stable
Classifier: Intended Audience :: Developers
Classifier: License :: OSI Approved :: MIT License
Classifier: Operating System :: OS Independent
Classifier: Programming Language :: Python :: 3
